README.md
setup.py
doulma/__init__.py
doulma/cli.py
doulma/exceptions.py
doulma/hashing.py
doulma/network.py
doulma/variables.py
doulma.egg-info/PKG-INFO
doulma.egg-info/SOURCES.txt
doulma.egg-info/dependency_links.txt
doulma.egg-info/top_level.txt
doulma/tests/__init__.py
doulma/tests/hashing_tests.py
doulma/tests/main_tests.py
doulma/tests/network_tests.py