Metadata-Version: 1.1
Name: doulma
Version: 0.1.0rc6
Summary: A Light Weight Python Utility Library.
Home-page: https://github.com/HussainARK/doulma
Author: HussainARK
Author-email: hussain.ark@yahoo.com
License: MIT
Platform: UNKNOWN
Classifier: Programming Language :: Python :: 3
Classifier: License :: OSI Approved :: MIT License
Classifier: Operating System :: OS Independent
